easy_augment/launch_tool.py
easy_augment/gui/aig_window.py
easy_augment/gui/aig_window_2.py
easy_augment/gui/annotations_gui.py
easy_augment/gui/camera_window.py
easy_augment/gui/gui_main.py
easy_augment/gui/progress_bar.py
easy_augment/pc_utils/capture_data.py
easy_augment/pc_utils/helper.py
easy_augment/utils/arguments.py
easy_augment/utils/generate_artificial_images.py
easy_augment/utils/generate_augmenter_list.py
easy_augment/utils/get_backgrounds_and_data.py
easy_augment/utils/labelme2voc.py
easy_augment/utils/make_semantic_labels.py
easy_augment/utils/object_details.py
easy_augment/utils/populate_src.py
easy_augment/utils/preprocessing.py
easy_augment/utils/saver.py
easy_augment/utils/visualizer.py
easy_augment-1.1.0.dist-info/LICENSE
easy_augment-1.1.0.dist-info/METADATA
easy_augment-1.1.0.dist-info/WHEEL
easy_augment-1.1.0.dist-info/entry_points.txt
easy_augment-1.1.0.dist-info/top_level.txt
easy_augment-1.1.0.dist-info/RECORD
