Metadata-Version: 2.1
Name: easy-augment
Version: 1.1.0
Summary: End to end software to capture new objects using RGBD camera  and augment them to get a annotated dataset to train deep nets.
Home-page: https://github.com/santoshreddy254/realsense_augmentor
Author: Santosh Muthireddy
Author-email: santoshreddy45@yahoo.com
License: MIT
Platform: UNKNOWN
Classifier: License :: OSI Approved :: MIT License
Classifier: Programming Language :: Python :: 3
Classifier: Programming Language :: Python :: 3.5
Requires-Dist: PyQt5
Requires-Dist: opencv-python
Requires-Dist: labelme
Requires-Dist: tqdm
Requires-Dist: joblib
Requires-Dist: scipy
Requires-Dist: matplotlib
Requires-Dist: imutils
Requires-Dist: numpy (>=1.16)
Requires-Dist: pascal-voc-tools
Requires-Dist: pascal-voc-writer
Requires-Dist: pytest-qt
Requires-Dist: pyrealsense2
Requires-Dist: python-pcl
